odoo/addons/mrp_subcontracting_inhibit/README.rst
odoo/addons/mrp_subcontracting_inhibit/__init__.py
odoo/addons/mrp_subcontracting_inhibit/__manifest__.py
odoo/addons/mrp_subcontracting_inhibit/i18n/es.po
odoo/addons/mrp_subcontracting_inhibit/i18n/it.po
odoo/addons/mrp_subcontracting_inhibit/i18n/mrp_subcontracting_inhibit.pot
odoo/addons/mrp_subcontracting_inhibit/i18n/pt_BR.po
odoo/addons/mrp_subcontracting_inhibit/models/__init__.py
odoo/addons/mrp_subcontracting_inhibit/models/product_product.py
odoo/addons/mrp_subcontracting_inhibit/models/product_supplierinfo.py
odoo/addons/mrp_subcontracting_inhibit/models/purchase_order.py
odoo/addons/mrp_subcontracting_inhibit/models/stock_location_route.py
odoo/addons/mrp_subcontracting_inhibit/models/stock_move.py
odoo/addons/mrp_subcontracting_inhibit/readme/CONFIGURE.md
odoo/addons/mrp_subcontracting_inhibit/readme/CONTRIBUTORS.md
odoo/addons/mrp_subcontracting_inhibit/readme/DESCRIPTION.md
odoo/addons/mrp_subcontracting_inhibit/readme/USAGE.md
odoo/addons/mrp_subcontracting_inhibit/static/description/icon.png
odoo/addons/mrp_subcontracting_inhibit/static/description/index.html
odoo/addons/mrp_subcontracting_inhibit/tests/__init__.py
odoo/addons/mrp_subcontracting_inhibit/tests/test_mrp_subcontracting_inhibit.py
odoo/addons/mrp_subcontracting_inhibit/views/product_supplierinfo_view.xml
odoo/addons/mrp_subcontracting_inhibit/views/purchase_order_view.xml
odoo/addons/mrp_subcontracting_inhibit/views/stock_location_route_view.xml
odoo_addon_mrp_subcontracting_inhibit-18.0.1.0.0.3.dist-info/METADATA
odoo_addon_mrp_subcontracting_inhibit-18.0.1.0.0.3.dist-info/WHEEL
odoo_addon_mrp_subcontracting_inhibit-18.0.1.0.0.3.dist-info/top_level.txt
odoo_addon_mrp_subcontracting_inhibit-18.0.1.0.0.3.dist-info/RECORD
